LICENSE
flask_caching_s3/__init__.py
flask_caching_s3-0.1.5.dist-info/LICENSE
flask_caching_s3-0.1.5.dist-info/METADATA
flask_caching_s3-0.1.5.dist-info/WHEEL
flask_caching_s3-0.1.5.dist-info/RECORD
