Metadata-Version: 2.1
Name: flask-caching-s3
Version: 0.1.5
Summary: An S3 adapter for the Flask-Caching framework
Home-page: https://github.com/fictivekin/flask-caching-s3
License: MIT
Keywords: flask,flask-caching,aws,s3,caching
Author: Joël Perras
Author-email: joel@fictivekin.com
Requires-Python: >=3.8,<4.0
Classifier: Environment :: Console
Classifier: License :: OSI Approved :: MIT License
Classifier: Operating System :: OS Independent
Classifier: Programming Language :: Python :: 3
Classifier: Programming Language :: Python :: 3.8
Classifier: Programming Language :: Python :: 3.9
Classifier: Programming Language :: Python :: 3.10
Classifier: Programming Language :: Python :: 3.11
Classifier: Topic :: Software Development :: Documentation
Classifier: Topic :: Software Development :: Libraries :: Python Modules
Requires-Dist: Flask-Caching (>=2.1.0,<3.0.0)
Requires-Dist: boto3 (>=1.26,<2.0)
Project-URL: Repository, https://github.com/fictivekin/flask-caching-s3
